in_silico_fate_mapping/__init__.py
in_silico_fate_mapping/_reader.py
in_silico_fate_mapping/_version.py
in_silico_fate_mapping/_widget.py
in_silico_fate_mapping/_writer.py
in_silico_fate_mapping/conftest.py
in_silico_fate_mapping/divergence.py
in_silico_fate_mapping/fast_radius_regression.py
in_silico_fate_mapping/fate_mapping.py
in_silico_fate_mapping/napari.yaml
in_silico_fate_mapping/widget_utils.py
in_silico_fate_mapping/_tests/__init__.py
in_silico_fate_mapping/_tests/test_divergence.py
in_silico_fate_mapping/_tests/test_fate_mapping.py
in_silico_fate_mapping/_tests/test_io.py
in_silico_fate_mapping/_tests/test_widget.py
in_silico_fate_mapping/cli/__init__.py
in_silico_fate_mapping/cli/divergence_cli.py
in_silico_fate_mapping-0.1.3.1.dist-info/licenses/LICENSE
in_silico_fate_mapping-0.1.3.1.dist-info/METADATA
in_silico_fate_mapping-0.1.3.1.dist-info/WHEEL
in_silico_fate_mapping-0.1.3.1.dist-info/entry_points.txt
in_silico_fate_mapping-0.1.3.1.dist-info/top_level.txt
in_silico_fate_mapping-0.1.3.1.dist-info/RECORD
