Metadata-Version: 2.4
Name: in-silico-fate-mapping
Version: 0.1.3.1
Summary: Interactive in silico fate mapping from tracking data
Home-page: https://github.com/royerlab/in-silico-fate-mapping
Author: Jordao Bragantini
Author-email: jordao.bragantini@czbiohub.org
License: BSD-3-Clause
Project-URL: Bug Tracker, https://github.com/royerlab/in-silico-fate-mapping/issues
Project-URL: Documentation, https://github.com/royerlab/in-silico-fate-mapping#README.md
Project-URL: Source Code, https://github.com/royerlab/in-silico-fate-mapping
Project-URL: User Support, https://github.com/royerlab/in-silico-fate-mapping/issues
Classifier: Development Status :: 2 - Pre-Alpha
Classifier: Framework :: napari
Classifier: Intended Audience :: Developers
Classifier: License :: OSI Approved :: BSD License
Classifier: Operating System :: OS Independent
Classifier: Programming Language :: Python
Classifier: Programming Language :: Python :: 3
Classifier: Programming Language :: Python :: 3 :: Only
Classifier: Programming Language :: Python :: 3.8
Classifier: Programming Language :: Python :: 3.9
Classifier: Programming Language :: Python :: 3.10
Classifier: Topic :: Scientific/Engineering :: Image Processing
Requires-Python: >=3.8
License-File: LICENSE
Requires-Dist: numpy
Requires-Dist: pandas
Requires-Dist: scikit-learn
Requires-Dist: zarr
Requires-Dist: magicgui
Requires-Dist: qtpy
Requires-Dist: napari
Requires-Dist: click
Provides-Extra: testing
Requires-Dist: tox; extra == "testing"
Requires-Dist: pytest; extra == "testing"
Requires-Dist: pytest-cov; extra == "testing"
Requires-Dist: pytest-qt; extra == "testing"
Requires-Dist: pyqt5; extra == "testing"
Dynamic: license-file
